MANIFEST.in
README.md
kuyruk_requeue.py
setup.py
Kuyruk_Requeue.egg-info/PKG-INFO
Kuyruk_Requeue.egg-info/SOURCES.txt
Kuyruk_Requeue.egg-info/dependency_links.txt
Kuyruk_Requeue.egg-info/entry_points.txt
Kuyruk_Requeue.egg-info/pbr.json
Kuyruk_Requeue.egg-info/requires.txt
Kuyruk_Requeue.egg-info/top_level.txt