Metadata-Version: 1.1
Name: Kuyruk-Requeue
Version: 1.2.0
Summary: Save failed tasks to Redis and requeue them.
Home-page: https://github.com/cenkalti/kuyruk-requeue
Author: Cenk Altı
Author-email: cenkalti@gmail.com
License: UNKNOWN
Keywords: kuyruk requeue
Platform: UNKNOWN
Classifier: Development Status :: 5 - Production/Stable
Classifier: License :: OSI Approved :: MIT License
Classifier: Operating System :: OS Independent
Classifier: Programming Language :: Python
Classifier: Programming Language :: Python :: 2.7
Classifier: Programming Language :: Python :: 3
Classifier: Topic :: Software Development :: Object Brokering
Classifier: Topic :: System :: Distributed Computing
